PathogenTrack/PathogenTrack.py
PathogenTrack/__init__.py
PathogenTrack-0.2.3.dist-info/LICENSE
PathogenTrack-0.2.3.dist-info/METADATA
PathogenTrack-0.2.3.dist-info/WHEEL
PathogenTrack-0.2.3.dist-info/entry_points.txt
PathogenTrack-0.2.3.dist-info/top_level.txt
PathogenTrack-0.2.3.dist-info/RECORD
