Metadata-Version: 2.1
Name: PathogenTrack
Version: 0.2.3
Summary: A pipeline to identify pathogenic microorganisms from scRNA-seq raw data
Home-page: https://github.com/ncrna/PathogenTrack
Author: Wei Zhang
Author-email: admin@ncrna.net
License: MIT
Project-URL: Quick Start, https://github.com/ncrna/PathogenTrack/blob/master/doc/QUICK_START.md
Project-URL: Bug Tracker, https://github.com/ncrna/PathogenTrack/issues
Platform: all
Classifier: Operating System :: OS Independent
Classifier: Development Status :: 4 - Beta
Classifier: License :: OSI Approved :: MIT License
Classifier: Topic :: Scientific/Engineering :: Bio-Informatics
Classifier: Programming Language :: Python :: 3
Requires-Python: >=3
License-File: LICENSE
Requires-Dist: biopython (>=1.78)
